auroraPrettyParser/__init__.py
aurora_prettyparser-1.0.4.dist-info/LICENSE
aurora_prettyparser-1.0.4.dist-info/METADATA
aurora_prettyparser-1.0.4.dist-info/WHEEL
aurora_prettyparser-1.0.4.dist-info/top_level.txt
aurora_prettyparser-1.0.4.dist-info/RECORD
