Metadata-Version: 2.1
Name: aurora-prettyparser
Version: 1.0.4
Summary: Parses Aurora responses into a list dictionaries with column names as keys
Home-page: https://github.com/QuiNovas/aurora-prettyparser
Author: Mathew Moon
Author-email: mmoon@quinovas.com
License: Apache 2.0
Platform: UNKNOWN
Classifier: Development Status :: 5 - Production/Stable
Classifier: Intended Audience :: Developers
Classifier: License :: OSI Approved :: Apache Software License
Classifier: Programming Language :: Python :: 3.7
